redisgl/__init__.py
redisgl/redisgl.py
redisgl-0.1.0.dist-info/LICENSE
redisgl-0.1.0.dist-info/METADATA
redisgl-0.1.0.dist-info/WHEEL
redisgl-0.1.0.dist-info/top_level.txt
redisgl-0.1.0.dist-info/RECORD
