Metadata-Version: 2.1
Name: redisgl
Version: 0.1.0
Summary: Redis-based robot visualizer
Author-email: Toki Migimatsu <takatoki@cs.stanford.edu>
License: MIT License
Classifier: Programming Language :: Python :: 3
Classifier: License :: OSI Approved :: MIT License
Classifier: Operating System :: OS Independent
Requires-Python: >=3.7
License-File: LICENSE
Requires-Dist: redis
Requires-Dist: ctrlutils
Requires-Dist: spatialdyn
